pipcentral.py
pipcentral-1.0.2.dist-info/licenses/LICENSE
pipcentral-1.0.2.dist-info/METADATA
pipcentral-1.0.2.dist-info/WHEEL
pipcentral-1.0.2.dist-info/entry_points.txt
pipcentral-1.0.2.dist-info/top_level.txt
pipcentral-1.0.2.dist-info/RECORD
