Metadata-Version: 2.4
Name: pipcentral
Version: 1.0.2
Summary: PipCentral is your one-stop tool for Python lovers
Home-page: https://github.com/Suresh-pyhobbyist/pipcentral
Author: Suresh_Pyhobbist
Classifier: Programming Language :: Python :: 3
Classifier: License :: OSI Approved :: MIT License
Classifier: Operating System :: OS Independent
Requires-Python: >=3.6
License-File: LICENSE
Requires-Dist: matplotlib==3.10.1
Requires-Dist: networkx==3.4.2
Requires-Dist: requests==2.32.3
Dynamic: author
Dynamic: classifier
Dynamic: description
Dynamic: description-content-type
Dynamic: home-page
Dynamic: license-file
Dynamic: requires-dist
Dynamic: requires-python
Dynamic: summary
